{
  "gitSyncId": "679a7543fd52167d9bf0eed4_1be41a6b-df95-4671-be7c-7b7a1d0767e1",
  "id": "Page1__$JSModule71$__$DateUtils2$_DateUtils2.isLeapYear",
  "isPublic": true,
  "moduleInstanceId": "Page1_JSModule71",
  "pluginId": "js-plugin",
  "pluginType": "JS",
  "rootModuleInstanceId": "Page1_JSModule71",
  "unpublishedAction": {
    "collectionId": "Page1__$JSModule71$__$DateUtils2$_DateUtils2",
    "confirmBeforeExecute": false,
    "contextType": "PAGE",
    "datasource": {
      "isAutoGenerated": false,
      "name": "UNUSED_DATASOURCE",
      "pluginId": "js-plugin"
    },
    "executeOnLoad": false,
    "fullyQualifiedName": "_$JSModule71$__$DateUtils2$_DateUtils2.isLeapYear",
    "name": "isLeapYear",
    "pageId": "Page1",
    "userSetOnLoad": false
  }
}